migrate/__init__.py
nimbus_migrate-0.1.0.dist-info/WHEEL
nimbus_migrate-0.1.0.dist-info/METADATA
nimbus_migrate-0.1.0.dist-info/RECORD
