Metadata-Version: 2.1
Name: nimbus-migrate
Version: 0.1.0
Summary: A simple migration library for nimbus cloud apps and services
License: MIT
Author: Zach Bullough
Author-email: zbullough@qmulosoft.com
Requires-Python: >=3.6,<4.0
Classifier: License :: OSI Approved :: MIT License
Classifier: Programming Language :: Python :: 3
Classifier: Programming Language :: Python :: 3.6
Classifier: Programming Language :: Python :: 3.7
Classifier: Programming Language :: Python :: 3.8
